oddsblaze/__init__.py
oddsblaze/async_client.py
oddsblaze/client.py
oddsblaze/exceptions.py
oddsblaze/py.typed
oddsblaze/settings.py
oddsblaze/models/__init__.py
oddsblaze/models/base.py
oddsblaze/models/consensus.py
oddsblaze/models/grader.py
oddsblaze/models/historical.py
oddsblaze/models/markets.py
oddsblaze/models/odds.py
oddsblaze/models/polled.py
oddsblaze/models/schedule.py
oddsblaze-0.2.0.dist-info/licenses/LICENSE
oddsblaze-0.2.0.dist-info/METADATA
oddsblaze-0.2.0.dist-info/WHEEL
oddsblaze-0.2.0.dist-info/top_level.txt
oddsblaze-0.2.0.dist-info/RECORD
