Metadata-Version: 2.4
Name: oddsblaze
Version: 0.2.0
Summary: Python Oddsblaze SDK
Author-email: reecetec <reece.tec@gmail.com>
Requires-Python: >=3.10
License-File: LICENSE
Requires-Dist: httpx>=0.28.1
Requires-Dist: pydantic>2
Requires-Dist: pydantic-settings>2
Dynamic: license-file
